<?xml version="1.0" encoding="UTF-8" standalone="yes"?>
<lookup_history>
    <day date="28-03-2023">
        <word word="hi" count="4"/>
        <word word="a" count="2"/>
        <word word="game" count="2"/>
        <word word="study" count="1"/>
        <word word="ăn uống" count="1"/>
        <word word="ăn" count="1"/>
        <word word="ấm" count="1"/>
        <word word="pro" count="2"/>
        <word word="huyền" count="1"/>
        <word word="ngủ" count="1"/>
        <word word="đi ngủ" count="1"/>
        <word word="đi" count="1"/>
        <word word="hello" count="4"/>
    </day>
    <day date="25-03-2023">
        <word word="hi" count="3"/>
        <word word="a" count="2"/>
        <word word="game" count="2"/>
        <word word="hello" count="4"/>
        <word word="ăn" count="1"/>
        <word word="pro" count="2"/>
    </day>
    <day date="29-03-2023">
        <word word="dd" count="1"/>
        <word word="studio" count="1"/>
        <word word="door" count="1"/>
        <word word="8-bit character code" count="1"/>
        <word word="game" count="3"/>
        <word word="study" count="3"/>
        <word word="fuck" count="3"/>
        <word word="FLOPS (floating-point operations per second)" count="1"/>
        <word word="convert" count="1"/>
        <word word="nguyên tắc" count="1"/>
        <word word="yểu" count="1"/>
        <word word="Linear estimator" count="1"/>
        <word word="byeee" count="1"/>
        <word word="keo" count="1"/>
        <word word="poor" count="1"/>
        <word word="đi chơi" count="1"/>
        <word word="âu yếm" count="1"/>
        <word word="alpha" count="1"/>
        <word word="thuốc nhỏ mắt" count="4"/>
        <word word="text" count="1"/>
        <word word="8-bit microcomputer" count="4"/>
        <word word="xin" count="1"/>
        <word word="international" count="3"/>
        <word word="helio" count="1"/>
        <word word="profit" count="1"/>
        <word word="introduction" count="1"/>
        <word word="sessile" count="1"/>
        <word word="hiếu" count="4"/>
        <word word="linear" count="1"/>
        <word word="hiên ngang" count="1"/>
        <word word="tenia" count="1"/>
        <word word="porcine" count="1"/>
        <word word="count" count="1"/>
        <word word="cây cỏ" count="1"/>
        <word word="pro" count="1"/>
        <word word="huyền" count="1"/>
        <word word="execute" count="1"/>
        <word word="đu đủ" count="1"/>
        <word word="diagram" count="1"/>
        <word word="size" count="1"/>
        <word word="pride" count="1"/>
        <word word="baby" count="2"/>
        <word word="online" count="1"/>
        <word word="keo cú" count="1"/>
        <word word="hello" count="5"/>
        <word word="window" count="1"/>
        <word word="under" count="1"/>
        <word word="tăm" count="1"/>
    </day>
    <day date="30-03-2023">
        <word word="hi" count="1"/>
        <word word="xin lỗi" count="1"/>
        <word word="game" count="1"/>
        <word word="sprinter" count="1"/>
        <word word="intern" count="1"/>
        <word word="bê trễ" count="1"/>
        <word word="trend" count="1"/>
        <word word="yểm" count="1"/>
        <word word="progamete" count="1"/>
        <word word="hỏi han" count="1"/>
        <word word="pro" count="1"/>
        <word word="programer" count="1"/>
        <word word="đi chơi" count="1"/>
        <word word="preprofessional" count="1"/>
        <word word="thuốc nhỏ mắt" count="1"/>
        <word word="hello" count="6"/>
        <word word="interested" count="1"/>
        <word word="ngu" count="1"/>
    </day>
</lookup_history>
